{
  "game_id": 6,
  "model_a": "a",
  "model_b": "g",
  "winner": "A",
  "winner_name": "a",
  "confidence": 0.75,
  "justification": "A is better overall because it at least acknowledges sp\u00b2 carbon, the 2D band, and crystalline order, while B completely misses the defining graphene signatures. Both fail scientific correctness on material and band identification, but A's output stays closer to relevant 2-D carbon physics. B's silicon conclusion is a more severe disconnect from the provided spectrum and ground truth.",
  "step1": {
    "A": "Incorrect: wrong material (bulk graphite), major band misassignment (G at 520 not 1580), no I(2D)/I(G) or FWHM analysis",
    "B": "Completely incorrect: identified as silicon, ignored all graphene bands (1580 & 2670 cm\u207b\u00b9)"
  },
  "step2": {
    "A": "Methodical structure but grounded in hallucinated Raman assignments; does not follow graphene physics",
    "B": "Internally consistent for Si but fails to address prominent carbon peaks; missing steps and data"
  },
  "step3": {
    "A": "Provides material, confidence, peaks, and some ratios but explanation is factually wrong",
    "B": "Concise with confidence and peaks but omits key evidence and misrepresents spectrum"
  },
  "thinking": "Neither candidate correctly identified the monolayer graphene per ground truth. Candidate A recognized sp\u00b2 carbon and the 2D overtone at ~2670 cm\u207b\u00b9 but catastrophically misassigned the G band to ~520 cm\u207b\u00b9 (calling 300 cm\u207b\u00b9 the D band), leading to bulk-graphite classification instead of monolayer. Candidate B focused solely on the ~522 cm\u207b\u00b9 peak as silicon while ignoring the clear G (~1580) and 2D (~2670) graphene signatures entirely. A is flawed yet engages with more of the actual spectral features; B is more logically coherent internally but wholly disconnected from the carbon bands and ground truth.",
  "elo_before": {
    "a": 27.07,
    "g": 50.0
  },
  "elo_after": {
    "a": 35.6,
    "g": 41.67
  }
}