{
  "game_id": 4,
  "model_a": "a",
  "model_b": "e",
  "winner": "B",
  "winner_name": "e",
  "confidence": 0.82,
  "justification": "B correctly identifies the material as h-BN and the dominant peak as the E\u2082g mode, while A hallucinates a graphite D-band. Although B errs on monolayer vs bulk, this is minor compared with A's total misclassification. Overall B is far closer to the ground-truth reference.",
  "step1": {
    "A": "Incorrect material (graphite instead of h-BN); confuses D-band with E\u2082g",
    "B": "Correct material (h-BN) and E\u2082g assignment; minor error on monolayer vs bulk"
  },
  "step2": {
    "A": "Systematic but built on false carbon-based premises; fails to distinguish h-BN from graphene",
    "B": "Methodical, physics-grounded chain of thought; correctly rules out carbon materials"
  },
  "step3": {
    "A": "Clear but entirely wrong classification; inappropriate confidence for incorrect material",
    "B": "States material, layer, confidence and key evidence; minor layer mismatch with GT"
  },
  "thinking": "Candidate A completely misidentifies the material as graphite, treating the 1369 cm\u207b\u00b9 peak as a D-band of sp\u00b2 carbon and invoking AB stacking; this is a fundamental error contradicting the ground-truth h-BN E\u2082g assignment. Candidate B correctly recognizes the single peak as the E\u2082g mode of h-BN, distinguishes it from graphene/carbon features, and uses position/FWHM arguments grounded in 2D-material Raman physics, though it incorrectly assigns monolayer instead of the GT-specified bulk. B is therefore superior on scientific correctness and reasoning quality despite the layer-number discrepancy; A fails the primary task of material identification.",
  "elo_before": {
    "a": 26.55,
    "e": 50.0
  },
  "elo_after": {
    "a": 19.09,
    "e": 57.29
  }
}